apything/__init__.py
apything/client.py
apything/config/config.yml
apything/endpoints/__init__.py
apything/endpoints/admin.py
apything/endpoints/documents.py
apything/endpoints/embed.py
apything/endpoints/system_settings.py
apything/endpoints/workspaces.py
apything/models/admin_model.py
apything/models/documents_model.py
apything/models/embed_model.py
apything/models/workspaces_model.py
apything/util/http_util.py
apything/workflows/chat_workflow.py
apything-0.2.0.dist-info/METADATA
apything-0.2.0.dist-info/WHEEL
apything-0.2.0.dist-info/licenses/LICENSE
apything-0.2.0.dist-info/RECORD
